{
  "schema_version": "1.1",
  "schema_id": "dealing_with_your_toddler_",
  "description": "Echologic Mercy Blade room for patient parenting, connection, and calm guidance",
  "description_vi": "Phòng Mercy Blade hỗ trợ nuôi dạy kiên nhẫn, kết nối, hướng dẫn bình tĩnh",
  "supported_languages": ["en", "vi"],
  "localization": { "default": "en", "fallback": "en" },
  "safety_disclaimer": "Educational guidance; not a substitute for professional, medical, or psychological advice.",
  "meta": {
    "created_at": "2025-10-05T23:39:00+09:00",
    "updated_at": "2025-10-05T23:45:00+09:00",
    "checksum_sha256": null,
    "meta_notes": "Keyword-driven; field-tested tone for toddler well-being | artifact_ids unique | batch=final/1 | batch_total=1"
  },
  "enums": {
    "tags": [
      "parenting",
      "communication",
      "emotions",
      "safety",
      "play",
      "routine",
      "learning",
      "health",
      "behavior",
      "growth"
    ],
    "urgency": ["immediate", "soon", "routine"],
    "severity_level": [1, 2, 3, 4, 5],
    "systems": ["psychology", "child_development", "family"]
  },
  "keywords": {
    "connection_play": {
      "en": [
        "connection_play",
        "floor_time",
        "join_play",
        "playful_presence",
        "follow_their_lead"
      ],
      "vi": [
        "kết_nối_qua_chơi",
        "chơi_sàn",
        "tham_gia_chơi",
        "hiện_diện_vui_tươi",
        "theo_nhịp_bé"
      ]
    },
    "tantrums": {
      "en": ["tantrums", "meltdowns", "outbursts", "fits", "temper_tantrums"],
      "vi": ["cơn_giận_dữ", "bùng_nổ", "bộc_phát", "cuồng_nộ", "nổi_cáu"]
    },
    "boundaries": {
      "en": ["boundaries", "limits", "rules", "guidelines", "restrictions"],
      "vi": ["ranh_giới", "giới_hạn", "quy_tắc", "hướng_dẫn", "hạn_chế"]
    },
    "empathy": {
      "en": ["empathy", "compassion", "understanding", "sympathy", "care"],
      "vi": [
        "đồng_cảm",
        "lòng_trắc_ẩn",
        "sự_thấu_hiểu",
        "thông_cảm",
        "quan_tâm"
      ]
    },
    "routine": {
      "en": ["routine", "schedule", "structure", "habit", "consistency"],
      "vi": ["thói_quen", "lịch_trình", "cấu_trúc", "nề_nếp", "nhất_quán"]
    },
    "safety": {
      "en": ["safety", "protection", "security", "well_being", "care"],
      "vi": ["an_toàn", "bảo_vệ", "an_ninh", "sức_khỏe", "chăm_sóc"]
    },
    "listening": {
      "en": [
        "listening",
        "hearing",
        "attention",
        "receptiveness",
        "understanding"
      ],
      "vi": ["lắng_nghe", "nghe", "chú_ý", "tiếp_nhận", "thấu_hiểu"]
    },
    "sharing": {
      "en": [
        "sharing",
        "cooperation",
        "taking_turns",
        "generosity",
        "collaboration"
      ],
      "vi": ["chia_sẻ", "hợp_tác", "luân_phiên", "hào_phóng", "cộng_tác"]
    },
    "sleep_routine": {
      "en": [
        "sleep_routine",
        "bedtime",
        "sleep_habits",
        "rest",
        "night_routine"
      ],
      "vi": ["thói_quen_ngủ", "giờ_ngủ", "lịch_ngủ", "ngủ_ngon", "nghỉ_ngơi"]
    },
    "choking_hazard": {
      "en": [
        "choking_hazard",
        "suffocation_risk",
        "airway_blockage",
        "choking_danger",
        "swallowing_risk"
      ],
      "vi": [
        "nguy_cơ_nghẹn",
        "rủi_ro_ngạt_thở",
        "tắc_nghẽn_đường_thở",
        "nguy_hiểm_nghẹn",
        "nguy_cơ_nuốt"
      ]
    },
    "positive_reinforcement": {
      "en": [
        "positive_reinforcement",
        "praise",
        "encouragement",
        "reward",
        "motivation"
      ],
      "vi": [
        "khuyến_khích_tích_cực",
        "khen_ngợi",
        "động_viên",
        "phần_thưởng",
        "động_lực"
      ]
    },
    "independence": {
      "en": [
        "independence",
        "autonomy",
        "self_reliance",
        "freedom",
        "self_sufficiency"
      ],
      "vi": ["độc_lập", "tự_chủ", "tự_lực", "tự_do", "tự_túc"]
    },
    "communication": {
      "en": [
        "communication",
        "talking",
        "dialogue",
        "expression",
        "conversation"
      ],
      "vi": ["giao_tiếp", "nói_chuyện", "đối_thoại", "biểu_đạt", "trò_chuyện"]
    },
    "patience": {
      "en": ["patience", "tolerance", "calmness", "endurance", "forbearance"],
      "vi": ["kiên_nhẫn", "khoan_dung", "bình_tĩnh", "chịu_đựng", "nhẫn_nại"]
    },
    "self_regulation": {
      "en": [
        "self_regulation",
        "self_control",
        "calmness",
        "self_discipline",
        "emotional_control"
      ],
      "vi": [
        "tự_điều_chỉnh",
        "tự_kiểm_soát",
        "bình_tĩnh",
        "tự_kỷ_luật",
        "kiểm_soát_cảm_xúc"
      ]
    },
    "playful_learning": {
      "en": [
        "playful_learning",
        "fun_education",
        "play_based_learning",
        "exploration",
        "curiosity"
      ],
      "vi": [
        "học_qua_chơi",
        "giáo_dục_vui_vẻ",
        "học_dựa_chơi",
        "khám_phá",
        "tò_mò"
      ]
    },
    "physical_safety": {
      "en": [
        "physical_safety",
        "child_protection",
        "injury_prevention",
        "safe_environment",
        "security"
      ],
      "vi": [
        "an_toàn_thể_chất",
        "bảo_vệ_trẻ",
        "ngăn_ngừa_thương_tích",
        "môi_trường_an_toàn",
        "an_ninh"
      ]
    },
    "emotional_safety": {
      "en": [
        "emotional_safety",
        "emotional_well_being",
        "security",
        "comfort",
        "stability"
      ],
      "vi": [
        "an_toàn_cảm_xúc",
        "sức_khỏe_cảm_xúc",
        "an_ninh",
        "thoải_mái",
        "ổn_định"
      ]
    },
    "discipline": {
      "en": ["discipline", "guidance", "correction", "training", "structure"],
      "vi": ["kỷ_luật", "hướng_dẫn", "sửa_sai", "huấn_luyện", "cấu_trúc"]
    },
    "exploration": {
      "en": ["exploration", "curiosity", "discovery", "adventure", "inquiry"],
      "vi": ["khám_phá", "tò_mò", "phát_hiện", "phiêu_lưu", "tìm_tòi"]
    },
    "child_neglect": {
      "en": [
        "child_neglect",
        "abandonment",
        "neglectful_care",
        "inattention",
        "disregard"
      ],
      "vi": ["bỏ_bê_trẻ", "bỏ_rơi", "chăm_sóc_thiếu_sót", "lơ_đễnh", "thờ_ơ"]
    },
    "frustration": {
      "en": ["frustration", "irritation", "upset", "annoyance", "anger"],
      "vi": ["bực_bội", "khó_chịu", "tức_giận", "phiền_muộn", "giận_dữ"]
    },
    "sleep_issues": {
      "en": [
        "sleep_issues",
        "insomnia",
        "sleep_problems",
        "restlessness",
        "sleep_deprivation"
      ],
      "vi": [
        "vấn_đề_giấc_ngủ",
        "mất_ngủ",
        "rối_loạn_giấc_ngủ",
        "bồn_chồn",
        "thiếu_ngủ"
      ]
    },
    "social_skills": {
      "en": [
        "social_skills",
        "interpersonal_skills",
        "friendship",
        "cooperation",
        "interaction"
      ],
      "vi": [
        "kỹ_năng_xã_hội",
        "kỹ_năng_giao_tiếp",
        "tình_bạn",
        "hợp_tác",
        "tương_tác"
      ]
    },
    "potty_training": {
      "en": [
        "potty_training",
        "toilet_training",
        "bathroom_habits",
        "potty_learning",
        "hygiene_training"
      ],
      "vi": [
        "tập_đi_vệ_sinh",
        "huấn_luyện_toilet",
        "thói_quen_vệ_sinh",
        "học_đi_vệ_sinh",
        "đào_tạo_vệ_sinh"
      ]
    },
    "eating_habits": {
      "en": [
        "eating_habits",
        "food_preferences",
        "mealtime_behavior",
        "nutrition",
        "diet"
      ],
      "vi": [
        "thói_quen_ăn_uống",
        "sở_thích_thực_phẩm",
        "hành_vi_bữa_ăn",
        "dinh_dưỡng",
        "chế_độ_ăn"
      ]
    },
    "separation_anxiety": {
      "en": [
        "separation_anxiety",
        "clinginess",
        "fear_of_separation",
        "attachment_issues",
        "distress"
      ],
      "vi": [
        "lo_âu_chia_cách",
        "bám_mẹ",
        "sợ_chia_cách",
        "vấn_đề_gắn_bó",
        "bất_an"
      ]
    },
    "screen_time": {
      "en": [
        "screen_time",
        "device_use",
        "digital_exposure",
        "media_time",
        "screen_exposure"
      ],
      "vi": [
        "thời_gian_màn_hình",
        "sử_dụng_thiết_bị",
        "tiếp_xúc_số",
        "thời_gian_truyền_thông",
        "phơi_bày_màn_hình"
      ]
    },
    "self_expression": {
      "en": [
        "self_expression",
        "creativity",
        "individuality",
        "voice",
        "self_statement"
      ],
      "vi": ["tự_biểu_đạt", "sáng_tạo", "cá_tính", "tiếng_nói", "tự_khẳng_định"]
    },
    "transitions": {
      "en": ["transitions", "change", "adjustment", "shifting", "adaptation"],
      "vi": [
        "chuyển_đổi",
        "thay_đổi",
        "điều_chỉnh",
        "chuyển_hướng",
        "thích_nghi"
      ]
    },
    "biting": {
      "en": [
        "biting",
        "nipping",
        "teething_behavior",
        "aggressive_biting",
        "mouthiness"
      ],
      "vi": ["cắn", "gặm", "hành_vi_mọc_răng", "cắn_tấn_công", "hành_vi_miệng"]
    },
    "hitting": {
      "en": [
        "hitting",
        "striking",
        "physical_aggression",
        "hitting_behavior",
        "lashing_out"
      ],
      "vi": [
        "đánh",
        "vung_tay",
        "tấn_công_thể_chất",
        "hành_vi_đánh",
        "bộc_phát"
      ]
    },
    "elopement": {
      "en": ["elopement", "running_away", "wandering", "fleeing", "straying"],
      "vi": ["bỏ_chạy", "chạy_trốn", "lang_thang", "trốn_đi", "lạc_lối"]
    },
    "curiosity": {
      "en": [
        "curiosity",
        "inquisitiveness",
        "interest",
        "exploration",
        "wonder"
      ],
      "vi": ["tò_mò", "hiếu_kỳ", "quan_tâm", "khám_phá", "kỳ_diệu"]
    },
    "gratitude": {
      "en": [
        "gratitude",
        "thankfulness",
        "appreciation",
        "gratefulness",
        "recognition"
      ],
      "vi": ["lòng_biết_ơn", "sự_cảm_kích", "tri_ân", "hàm_ơn", "ghi_nhận"]
    },
    "cooperation": {
      "en": [
        "cooperation",
        "teamwork",
        "collaboration",
        "working_together",
        "partnership"
      ],
      "vi": [
        "hợp_tác",
        "làm_việc_nhóm",
        "cộng_tác",
        "làm_việc_cùng_nhau",
        "đồng_hành"
      ]
    },
    "language_development": {
      "en": [
        "language_development",
        "speech_growth",
        "communication_skills",
        "talking",
        "verbal_skills"
      ],
      "vi": [
        "phát_triển_ngôn_ngữ",
        "tăng_trưởng_lời_nói",
        "kỹ_năng_giao_tiếp",
        "nói_chuyện",
        "kỹ_năng_lời_nói"
      ]
    },
    "motor_skills": {
      "en": [
        "motor_skills",
        "physical_development",
        "coordination",
        "movement",
        "dexterity"
      ],
      "vi": [
        "kỹ_năng_vận_động",
        "phát_triển_thể_chất",
        "phối_hợp",
        "chuyển_động",
        "khéo_léo"
      ]
    },
    "parental_stress": {
      "en": [
        "parental_stress",
        "caregiver_burden",
        "parenting_pressure",
        "stress",
        "anxiety"
      ],
      "vi": [
        "căng_thẳng_cha_mẹ",
        "gánh_nặng_chăm_sóc",
        "áp_lực_nuôi_dạy",
        "căng_thẳng",
        "lo_âu"
      ]
    },
    "trust": {
      "en": ["trust", "confidence", "reliance", "faith", "belief"],
      "vi": [
        "tin_tưởng",
        "lòng_tin",
        "sự_phụ_thuộc",
        "niềm_tin",
        "niềm_vững_chắc"
      ]
    }
  },
  "room_essay": {
    "format": "markdown",
    "en": "# Parenting Your Toddler with Patience and Connection\n\nRaising a toddler can feel like a big adventure. They are curious, full of energy, and learning fast. This room offers practical ideas to help you connect with your child, guide their behavior, and keep them safe. The tips here focus on patience, play, and building trust, with simple steps to make parenting easier.\n\n### Connecting Through Play and Routines\nPlay is a great way to bond with your toddler. Try joining them in their games, like building blocks or pretending. Follow their lead and be present—it helps them feel loved. For example, the room suggests \"connection play\" to build stronger bonds. Routines also help. A steady bedtime or mealtime schedule gives your toddler a sense of safety. Stick to simple routines, like reading a story before bed, to make daily life smoother.\n\n### Guiding Behavior with Kindness\nToddlers often have big emotions, like tantrums or frustration. Stay calm and name their feelings, like saying, “You’re upset because you want the toy.” This shows empathy and helps them learn to manage emotions. Set clear boundaries, like “We don’t hit,” and explain why in simple words. Use positive reinforcement—praise them when they share or try something new. The room’s tips on discipline and self-regulation offer ways to guide without harsh words.\n\n### Keeping Safety First\nSafety is key for toddlers, who love to explore. Check your home for choking hazards, like small toys, and always watch them during meals. For bigger concerns, like elopement or neglect, act fast and call a hotline if needed. The room’s safety entries, like “physical safety” and “choking hazard,” remind you to stay alert and teach safe habits early.\n\n### Research and Decision-Making\nIf you’re unsure about a parenting choice, like screen time or potty training, take time to research. Look into trusted books or websites on child development. Talk to other parents or a pediatrician for advice. Use the room’s entries, like “social skills” or “eating habits,” to guide your focus. Decide what feels right for your child, but avoid rushing into strict rules. For example, limiting screen time might work better than banning it completely.\n\n### Ethics, Privacy, and Safety\nAlways respect your toddler’s feelings and privacy. Avoid sharing their struggles online without careful thought. Safety includes emotional care—build trust by listening and comforting them. If you feel stressed, take a moment for yourself. The room’s “parental stress” entry suggests self-care to stay calm and present.\n\n### Next Steps\nStart with one or two ideas from this room, like playing together or setting a bedtime routine. Try them for a week and see what works. If your toddler has tantrums, practice staying calm and redirecting them. For bigger concerns, like sleep issues or biting, check the room’s entries for specific tips. Keep learning and stay patient—parenting is a journey, and small steps make a big difference.\n\nThis guidance is not a replacement for professional advice. If you have concerns about your toddler’s health or behavior, talk to a doctor or specialist. Stay connected with your child, and enjoy the moments you share.",
    "vi": "# Nuôi Dạy Bé Với Sự Kiên Nhẫn và Kết Nối\n\nChăm sóc một em bé mới biết đi là một cuộc phiêu lưu đầy màu sắc. Bé tò mò, tràn đầy năng lượng và học rất nhanh. Phòng này cung cấp các ý tưởng thực tế giúp bạn kết nối với con, hướng dẫn hành vi và bảo đảm an toàn. Các gợi ý tập trung vào kiên nhẫn, vui chơi và xây dựng lòng tin, với những bước đơn giản để việc nuôi dạy trở nên nhẹ nhàng hơn.\n\n### Kết Nối Qua Chơi và Thói Quen\nChơi là cách tuyệt vời để gắn kết với bé. Hãy tham gia vào trò chơi của con—xếp khối, đóng vai, giả vờ… Đi theo nhịp của bé và hiện diện trọn vẹn; điều đó giúp bé cảm nhận tình yêu và sự quan tâm. Ví dụ, mục “kết nối qua chơi” trong phòng gợi ý các cách xây dựng mối quan hệ bền chặt. Thói quen cũng rất quan trọng: lịch ngủ và giờ ăn ổn định giúp bé thấy an toàn. Duy trì những thói quen đơn giản, như đọc truyện trước giờ ngủ, để nhịp sinh hoạt hằng ngày trôi chảy hơn.\n\n### Hướng Dẫn Hành Vi Với Sự Tử Tế\nTrẻ nhỏ thường có cảm xúc mãnh liệt, như giận dữ hoặc bực bội. Hãy bình tĩnh và gọi tên cảm xúc của bé—“Con buồn vì muốn món đồ chơi đó”—để thể hiện sự thấu cảm và giúp con học tự điều chỉnh. Đặt ranh giới rõ ràng, chẳng hạn “Chúng ta không đánh bạn,” và giải thích bằng ngôn ngữ đơn giản. Ưu tiên khuyến khích tích cực: khen khi bé chia sẻ hoặc dũng cảm thử điều mới. Các mục về kỷ luật và tự điều chỉnh trong phòng sẽ giúp bạn dẫn dắt mà không cần lời lẽ nặng nề.\n\n### Đặt An Toàn Lên Hàng Đầu\nAn toàn đặc biệt quan trọng vì bé rất thích khám phá. Kiểm tra nhà để tránh nguy cơ hóc nghẹn (đồ chơi nhỏ, miếng thức ăn…) và luôn trông chừng khi bé ăn. Với những tình huống nghiêm trọng như chạy ra đường hay dấu hiệu bị bỏ bê, hãy hành động ngay và gọi các đường dây hỗ trợ khi cần. Các mục “an toàn thể chất” và “nguy cơ hóc nghẹn” trong phòng nhắc bạn luôn cảnh giác và dạy bé thói quen an toàn từ sớm.\n\n### Nghiên Cứu và Ra Quyết Định\nNếu còn phân vân trước một lựa chọn nuôi dạy—như thời gian màn hình hay tập bô—hãy dành thời gian tìm hiểu. Tham khảo sách uy tín hoặc các trang web về phát triển trẻ. Trao đổi với phụ huynh khác hoặc bác sĩ nhi khoa để có thêm góc nhìn. Dựa vào các mục trong phòng, như “kỹ năng xã hội” hay “thói quen ăn uống,” để định hướng. Quyết định điều phù hợp với bé nhưng tránh áp đặt quy tắc cứng nhắc. Ví dụ, hạn chế thời gian màn hình thường hữu ích hơn là cấm tuyệt đối.\n\n### Đạo Đức, Quyền Riêng Tư và An Toàn\nLuôn tôn trọng cảm xúc và quyền riêng tư của bé. Tránh chia sẻ khó khăn của con lên mạng khi chưa cân nhắc kỹ hậu quả lâu dài. An toàn cũng bao gồm chăm sóc cảm xúc—xây dựng lòng tin bằng cách lắng nghe, an ủi và phản hồi dịu dàng. Nếu bạn thấy căng thẳng, hãy dành thời gian cho bản thân. Mục “căng thẳng của cha mẹ” trong phòng gợi ý các cách tự chăm sóc để bạn giữ được bình tĩnh và sự hiện diện.\n\n### Bước Tiếp Theo\nBắt đầu với một–hai ý tưởng từ phòng này, như chơi cùng bé hoặc thiết lập thói quen giờ ngủ. Thử trong một tuần và quan sát điều gì hiệu quả. Khi bé nổi giận, luyện cách giữ bình tĩnh và chuyển hướng hoạt động. Với các vấn đề lớn hơn—như khó ngủ hoặc cắn—hãy xem các mục chuyên biệt trong phòng. Tiếp tục học hỏi và kiên nhẫn: nuôi dạy là một hành trình, và những bước nhỏ tạo nên khác biệt lớn.\n\nTài liệu này không thay thế cho lời khuyên chuyên môn. Nếu lo lắng về sức khỏe hoặc hành vi của bé, hãy trao đổi với bác sĩ hoặc chuyên gia. Hãy nuôi dưỡng sự kết nối với con và tận hưởng những khoảnh khắc bên nhau.",
    "word_count_en": 594,
    "word_count_vi": 602,
    "updated_at": "2025-10-10T08:27:00Z"
  },
  "ui_triggers": {
    "essay_offer": {
      "enabled": true,
      "criteria": {
        "min_entries_total": 6,
        "min_distinct_buckets": 3,
        "max_prior_briefs_shown": 0,
        "max_recency_minutes": 720
      },
      "behavior": {
        "mode": "chip_suggest",
        "snooze_minutes": 1440,
        "pin_to_canvas": true
      }
    }
  },
  "entries": [
    {
      "slug": "connection_play",
      "title": {
        "en": "Building Connection Through Play",
        "vi": "Xây dựng Kết nối Qua Chơi"
      },
      "copy": {
        "en": "Join their play, follow their lead, and be fully present. Dare: Play daily.",
        "vi": "Tham gia chơi, theo nhịp bé, hiện diện trọn vẹn. Dám: Chơi hàng ngày."
      },
      "attribution": "Best Practices / Thực hành tốt nhất",
      "tags": ["parenting", "play"],
      "urgency": "routine",
      "severity_level": 2,
      "systems": ["child_development", "family"],
      "metadata": { "topic": "play", "flags": [] },
      "artifact_id": "2f1a8c60-3e7b-4a1f-9a2c-a9b2c3d4e501",
      "artifact_version_id": "2f1a8c60-3e7b-4a1f-9a2c-a9b2c3d4e501-v001",
      "created_at": "2025-10-05T23:39:00+09:00",
      "updated_at": "2025-10-05T23:45:00+09:00"
    },
    {
      "slug": "tantrums",
      "title": {
        "en": "Managing Toddler Tantrums",
        "vi": "Quản lý Cơn Giận của Bé"
      },
      "copy": {
        "en": "Stay calm, validate feelings, and redirect gently. Dare: Breathe through chaos.",
        "vi": "Bình tĩnh, xác nhận cảm xúc, chuyển hướng nhẹ nhàng. Dám: Hít thở qua hỗn loạn."
      },
      "attribution": "Best Practices / Thực hành tốt nhất",
      "tags": ["parenting", "emotions"],
      "urgency": "soon",
      "severity_level": 3,
      "systems": ["psychology", "child_development"],
      "metadata": { "topic": "behavior", "flags": ["sensitive"] },
      "artifact_id": "3a7c2b11-9f5d-4f3a-94b8-8a0b9e2d4f02",
      "artifact_version_id": "3a7c2b11-9f5d-4f3a-94b8-8a0b9e2d4f02-v001",
      "created_at": "2025-10-05T23:39:00+09:00",
      "updated_at": "2025-10-05T23:45:00+09:00"
    },
    {
      "slug": "boundaries",
      "title": {
        "en": "Setting Toddler Boundaries",
        "vi": "Thiết lập Ranh giới cho Bé"
      },
      "copy": {
        "en": "Set clear rules, explain simply, and enforce consistently. Dare: Stay firm lovingly.",
        "vi": "Đặt quy tắc rõ, giải thích đơn giản, thực thi nhất quán. Dám: Kiên định yêu thương."
      },
      "attribution": "Best Practices / Thực hành tốt nhất",
      "tags": ["parenting", "behavior"],
      "urgency": "routine",
      "severity_level": 2,
      "systems": ["child_development", "family"],
      "metadata": { "topic": "discipline", "flags": [] },
      "artifact_id": "4c1d5e22-8a0f-4b8c-9d2e-b8c1a2f3e503",
      "artifact_version_id": "4c1d5e22-8a0f-4b8c-9d2e-b8c1a2f3e503-v001",
      "created_at": "2025-10-05T23:39:00+09:00",
      "updated_at": "2025-10-05T23:45:00+09:00"
    },
    {
      "slug": "empathy",
      "title": {
        "en": "Showing Empathy to Your Toddler",
        "vi": "Thể hiện Đồng cảm với Bé"
      },
      "copy": {
        "en": "Name their feelings, comfort gently, and model kindness. Dare: Connect through emotions.",
        "vi": "Gọi tên cảm xúc, an ủi nhẹ nhàng, làm gương tử tế. Dám: Kết nối qua cảm xúc."
      },
      "attribution": "Best Practices / Thực hành tốt nhất",
      "tags": ["parenting", "emotions"],
      "urgency": "routine",
      "severity_level": 2,
      "systems": ["psychology", "child_development"],
      "metadata": { "topic": "emotional_support", "flags": [] },
      "artifact_id": "5d2e6f33-7b1a-4c9d-8e3f-98c2b3a4f504",
      "artifact_version_id": "5d2e6f33-7b1a-4c9d-8e3f-98c2b3a4f504-v001",
      "created_at": "2025-10-05T23:39:00+09:00",
      "updated_at": "2025-10-05T23:45:00+09:00"
    },
    {
      "slug": "routine",
      "title": {
        "en": "Establishing Toddler Routines",
        "vi": "Thiết lập Thói quen cho Bé"
      },
      "copy": {
        "en": "Create consistent schedules, model structure, and be patient. Dare: Stick to routines.",
        "vi": "Tạo lịch trình nhất quán, làm gương cấu trúc, kiên nhẫn. Dám: Duy trì thói quen."
      },
      "attribution": "Best Practices / Thực hành tốt nhất",
      "tags": ["parenting", "routine"],
      "urgency": "routine",
      "severity_level": 2,
      "systems": ["child_development", "family"],
      "metadata": { "topic": "routine", "flags": [] },
      "artifact_id": "6e3f7a44-6c2b-4da0-8f4a-89d3c4b5e505",
      "artifact_version_id": "6e3f7a44-6c2b-4da0-8f4a-89d3c4b5e505-v001",
      "created_at": "2025-10-05T23:39:00+09:00",
      "updated_at": "2025-10-05T23:45:00+09:00"
    },
    {
      "slug": "safety",
      "title": {
        "en": "Ensuring Toddler Safety",
        "vi": "Đảm bảo An toàn cho Bé"
      },
      "copy": {
        "en": "Childproof spaces, supervise closely, and teach safe behaviors. Dare: Call hotline; ensure safety.",
        "vi": "Bảo vệ không gian, giám sát chặt chẽ, dạy hành vi an toàn. Dám: Gọi đường dây nóng; đảm bảo an toàn."
      },
      "attribution": "Best Practices / Thực hành tốt nhất",
      "tags": ["parenting", "safety"],
      "urgency": "immediate",
      "severity_level": 5,
      "systems": ["child_development", "family"],
      "metadata": { "topic": "safety", "flags": ["crisis"] },
      "artifact_id": "7f4a8b55-5d3c-4eb1-8a5b-78e4d5c6b506",
      "artifact_version_id": "7f4a8b55-5d3c-4eb1-8a5b-78e4d5c6b506-v001",
      "created_at": "2025-10-05T23:39:00+09:00",
      "updated_at": "2025-10-05T23:45:00+09:00"
    },
    {
      "slug": "listening",
      "title": { "en": "Listening to Your Toddler", "vi": "Lắng nghe Bé" },
      "copy": {
        "en": "Get down to their level, listen patiently, and respond gently. Dare: Hear their heart.",
        "vi": "Hạ thấp người, lắng nghe kiên nhẫn, phản hồi nhẹ nhàng. Dám: Nghe trái tim bé."
      },
      "attribution": "Best Practices / Thực hành tốt nhất",
      "tags": ["parenting", "communication"],
      "urgency": "routine",
      "severity_level": 2,
      "systems": ["psychology", "child_development"],
      "metadata": { "topic": "communication", "flags": [] },
      "artifact_id": "8a5b9c66-4e4d-4fc2-8b6c-67f5e6d7a507",
      "artifact_version_id": "8a5b9c66-4e4d-4fc2-8b6c-67f5e6d7a507-v001",
      "created_at": "2025-10-05T23:39:00+09:00",
      "updated_at": "2025-10-05T23:45:00+09:00"
    },
    {
      "slug": "sharing",
      "title": { "en": "Teaching Sharing to Toddlers", "vi": "Dạy Bé Chia sẻ" },
      "copy": {
        "en": "Model sharing, praise cooperation, and guide turn-taking gently. Dare: Practice daily sharing.",
        "vi": "Làm gương chia sẻ, khen hợp tác, hướng dẫn luân phiên nhẹ nhàng. Dám: Thực hành chia sẻ hàng ngày."
      },
      "attribution": "Best Practices / Thực hành tốt nhất",
      "tags": ["parenting", "behavior"],
      "urgency": "routine",
      "severity_level": 2,
      "systems": ["child_development", "psychology"],
      "metadata": { "topic": "social_skills", "flags": [] },
      "artifact_id": "9b6cad77-3f5e-45d3-9c7d-56a6f7e8c508",
      "artifact_version_id": "9b6cad77-3f5e-45d3-9c7d-56a6f7e8c508-v001",
      "created_at": "2025-10-05T23:39:00+09:00",
      "updated_at": "2025-10-05T23:45:00+09:00"
    },
    {
      "slug": "sleep_routine",
      "title": {
        "en": "Creating a Sleep Routine",
        "vi": "Tạo Thói quen Ngủ cho Bé"
      },
      "copy": {
        "en": "Set a calm bedtime, be consistent, and comfort gently. Dare: Stick to bedtime.",
        "vi": "Đặt giờ ngủ yên tĩnh, nhất quán, an ủi nhẹ nhàng. Dám: Duy trì giờ ngủ."
      },
      "attribution": "Best Practices / Thực hành tốt nhất",
      "tags": ["parenting", "routine"],
      "urgency": "routine",
      "severity_level": 2,
      "systems": ["child_development", "family"],
      "metadata": { "topic": "routine", "flags": [] },
      "artifact_id": "0c7dbe88-2a6f-46e4-8d8e-45b7c8d9b509",
      "artifact_version_id": "0c7dbe88-2a6f-46e4-8d8e-45b7c8d9b509-v001",
      "created_at": "2025-10-05T23:39:00+09:00",
      "updated_at": "2025-10-05T23:45:00+09:00"
    },
    {
      "slug": "choking_hazard",
      "title": {
        "en": "Preventing Choking Hazards",
        "vi": "Ngăn ngừa Nguy cơ Nghẹn"
      },
      "copy": {
        "en": "Check food sizes, supervise eating, and remove small objects. Dare: Call hotline; ensure safety.",
        "vi": "Kiểm tra kích thước thức ăn, giám sát ăn, loại bỏ vật nhỏ. Dám: Gọi đường dây nóng; đảm bảo an toàn."
      },
      "attribution": "Best Practices / Thực hành tốt nhất",
      "tags": ["parenting", "safety"],
      "urgency": "immediate",
      "severity_level": 5,
      "systems": ["child_development", "family"],
      "metadata": { "topic": "safety", "flags": ["crisis"] },
      "artifact_id": "1d8ece99-1b70-47f5-9e9f-34c8d9eab50a",
      "artifact_version_id": "1d8ece99-1b70-47f5-9e9f-34c8d9eab50a-v001",
      "created_at": "2025-10-05T23:39:00+09:00",
      "updated_at": "2025-10-05T23:45:00+09:00"
    },
    {
      "slug": "positive_reinforcement",
      "title": {
        "en": "Using Positive Reinforcement",
        "vi": "Sử dụng Khuyến khích Tích cực"
      },
      "copy": {
        "en": "Praise good behavior, reward effort, and be specific. Dare: Celebrate small wins.",
        "vi": "Khen hành vi tốt, thưởng nỗ lực, cụ thể rõ ràng. Dám: Tôn vinh chiến thắng nhỏ."
      },
      "attribution": "Best Practices / Thực hành tốt nhất",
      "tags": ["parenting", "behavior"],
      "urgency": "routine",
      "severity_level": 2,
      "systems": ["psychology", "child_development"],
      "metadata": { "topic": "behavior", "flags": [] },
      "artifact_id": "2e9fdfa0-0c81-48a6-8b10-23d9eafb0511",
      "artifact_version_id": "2e9fdfa0-0c81-48a6-8b10-23d9eafb0511-v001",
      "created_at": "2025-10-05T23:39:00+09:00",
      "updated_at": "2025-10-05T23:45:00+09:00"
    },
    {
      "slug": "independence",
      "title": {
        "en": "Encouraging Toddler Independence",
        "vi": "Khuyến khích Bé Độc lập"
      },
      "copy": {
        "en": "Allow small choices, support efforts, and praise progress. Dare: Let them try.",
        "vi": "Cho phép lựa chọn nhỏ, hỗ trợ nỗ lực, khen tiến bộ. Dám: Để bé thử."
      },
      "attribution": "Best Practices / Thực hành tốt nhất",
      "tags": ["parenting", "growth"],
      "urgency": "routine",
      "severity_level": 2,
      "systems": ["child_development", "psychology"],
      "metadata": { "topic": "growth", "flags": [] },
      "artifact_id": "3fa0e0b1-fd92-41b7-8c21-12ea0bfc0512",
      "artifact_version_id": "3fa0e0b1-fd92-41b7-8c21-12ea0bfc0512-v001",
      "created_at": "2025-10-05T23:39:00+09:00",
      "updated_at": "2025-10-05T23:45:00+09:00"
    },
    {
      "slug": "communication",
      "title": {
        "en": "Communicating with Your Toddler",
        "vi": "Giao tiếp với Bé"
      },
      "copy": {
        "en": "Use simple words, be patient, and encourage expression. Dare: Speak their language.",
        "vi": "Dùng từ đơn giản, kiên nhẫn, khuyến khích biểu đạt. Dám: Nói ngôn ngữ của bé."
      },
      "attribution": "Best Practices / Thực hành tốt nhất",
      "tags": ["parenting", "communication"],
      "urgency": "routine",
      "severity_level": 2,
      "systems": ["psychology", "child_development"],
      "metadata": { "topic": "communication", "flags": [] },
      "artifact_id": "4ab1f1c2-ec03-42c8-8d32-01fb1c0d0513",
      "artifact_version_id": "4ab1f1c2-ec03-42c8-8d32-01fb1c0d0513-v001",
      "created_at": "2025-10-05T23:39:00+09:00",
      "updated_at": "2025-10-05T23:45:00+09:00"
    },
    {
      "slug": "patience",
      "title": {
        "en": "Practicing Patience with Toddlers",
        "vi": "Thực hành Kiên nhẫn với Bé"
      },
      "copy": {
        "en": "Stay calm, model patience, and give them time. Dare: Breathe through challenges.",
        "vi": "Bình tĩnh, làm gương kiên nhẫn, cho bé thời gian. Dám: Hít thở qua thử thách."
      },
      "attribution": "Best Practices / Thực hành tốt nhất",
      "tags": ["parenting", "emotions"],
      "urgency": "routine",
      "severity_level": 2,
      "systems": ["psychology", "child_development"],
      "metadata": { "topic": "emotional_regulation", "flags": [] },
      "artifact_id": "5bc2g2d3-dd14-43d9-9e43-f0ac2d1e0514",
      "artifact_version_id": "5bc2g2d3-dd14-43d9-9e43-f0ac2d1e0514-v001",
      "created_at": "2025-10-05T23:39:00+09:00",
      "updated_at": "2025-10-05T23:45:00+09:00"
    },
    {
      "slug": "self_regulation",
      "title": {
        "en": "Teaching Toddler Self-Regulation",
        "vi": "Dạy Bé Tự Điều chỉnh"
      },
      "copy": {
        "en": "Model calm, teach breathing, and guide emotional control. Dare: Practice regulation daily.",
        "vi": "Làm gương bình tĩnh, dạy hít thở, hướng dẫn kiểm soát cảm xúc. Dám: Thực hành điều chỉnh hàng ngày."
      },
      "attribution": "Best Practices / Thực hành tốt nhất",
      "tags": ["parenting", "emotions"],
      "urgency": "routine",
      "severity_level": 2,
      "systems": ["psychology", "child_development"],
      "metadata": { "topic": "emotional_regulation", "flags": [] },
      "artifact_id": "6cd3e3f4-cc25-44ea-8a54-e1bd3e2f0515",
      "artifact_version_id": "6cd3e3f4-cc25-44ea-8a54-e1bd3e2f0515-v001",
      "created_at": "2025-10-05T23:39:00+09:00",
      "updated_at": "2025-10-05T23:45:00+09:00"
    },
    {
      "slug": "playful_learning",
      "title": {
        "en": "Encouraging Playful Learning",
        "vi": "Khuyến khích Học Qua Chơi"
      },
      "copy": {
        "en": "Use play to teach, encourage curiosity, and celebrate discoveries. Dare: Explore together.",
        "vi": "Dùng chơi để dạy, khuyến khích tò mò, tôn vinh khám phá. Dám: Khám phá cùng bé."
      },
      "attribution": "Best Practices / Thực hành tốt nhất",
      "tags": ["parenting", "learning"],
      "urgency": "routine",
      "severity_level": 2,
      "systems": ["child_development", "psychology"],
      "metadata": { "topic": "learning", "flags": [] },
      "artifact_id": "7de4f405-bb36-45fb-8b65-d2ce4f300516",
      "artifact_version_id": "7de4f405-bb36-45fb-8b65-d2ce4f300516-v001",
      "created_at": "2025-10-05T23:39:00+09:00",
      "updated_at": "2025-10-05T23:45:00+09:00"
    },
    {
      "slug": "physical_safety",
      "title": {
        "en": "Ensuring Physical Safety",
        "vi": "Đảm bảo An toàn Thể chất"
      },
      "copy": {
        "en": "Secure hazards, supervise closely, and teach safe actions. Dare: Call hotline; ensure safety.",
        "vi": "Bảo vệ nguy cơ, giám sát chặt, dạy hành động an toàn. Dám: Gọi đường dây nóng; đảm bảo an toàn."
      },
      "attribution": "Best Practices / Thực hành tốt nhất",
      "tags": ["parenting", "safety"],
      "urgency": "immediate",
      "severity_level": 5,
      "systems": ["child_development", "family"],
      "metadata": { "topic": "safety", "flags": ["crisis"] },
      "artifact_id": "8ef50516-aa47-461c-9c76-c3df50310517",
      "artifact_version_id": "8ef50516-aa47-461c-9c76-c3df50310517-v001",
      "created_at": "2025-10-05T23:39:00+09:00",
      "updated_at": "2025-10-05T23:45:00+09:00"
    },
    {
      "slug": "emotional_safety",
      "title": {
        "en": "Creating Emotional Safety",
        "vi": "Tạo An toàn Cảm xúc"
      },
      "copy": {
        "en": "Offer comfort, validate feelings, and build secure attachment. Dare: Be their safe space.",
        "vi": "An ủi, xác nhận cảm xúc, xây dựng gắn bó an toàn. Dám: Là không gian an toàn."
      },
      "attribution": "Best Practices / Thực hành tốt nhất",
      "tags": ["parenting", "emotions"],
      "urgency": "routine",
      "severity_level": 2,
      "systems": ["psychology", "child_development"],
      "metadata": { "topic": "emotional_support", "flags": [] },
      "artifact_id": "9f061627-9948-472d-8d87-b4e051420518",
      "artifact_version_id": "9f061627-9948-472d-8d87-b4e051420518-v001",
      "created_at": "2025-10-05T23:39:00+09:00",
      "updated_at": "2025-10-05T23:45:00+09:00"
    },
    {
      "slug": "discipline",
      "title": { "en": "Disciplining Your Toddler", "vi": "Kỷ luật Bé" },
      "copy": {
        "en": "Use gentle guidance, set clear limits, and redirect behavior. Dare: Discipline with love.",
        "vi": "Hướng dẫn nhẹ nhàng, đặt giới hạn rõ, chuyển hướng hành vi. Dám: Kỷ luật với tình yêu."
      },
      "attribution": "Best Practices / Thực hành tốt nhất",
      "tags": ["parenting", "behavior"],
      "urgency": "routine",
      "severity_level": 2,
      "systems": ["child_development", "psychology"],
      "metadata": { "topic": "discipline", "flags": [] },
      "artifact_id": "a0072738-8859-43ae-9e98-a5f162530519",
      "artifact_version_id": "a0072738-8859-43ae-9e98-a5f162530519-v001",
      "created_at": "2025-10-05T23:39:00+09:00",
      "updated_at": "2025-10-05T23:45:00+09:00"
    },
    {
      "slug": "exploration",
      "title": {
        "en": "Encouraging Safe Exploration",
        "vi": "Khuyến khích Khám phá An toàn"
      },
      "copy": {
        "en": "Support curiosity, provide safe spaces, and supervise closely. Dare: Explore with them.",
        "vi": "Hỗ trợ tò mò, cung cấp không gian an toàn, giám sát chặt. Dám: Khám phá cùng bé."
      },
      "attribution": "Best Practices / Thực hành tốt nhất",
      "tags": ["parenting", "learning"],
      "urgency": "routine",
      "severity_level": 2,
      "systems": ["child_development", "psychology"],
      "metadata": { "topic": "learning", "flags": [] },
      "artifact_id": "b1183849-776a-44bf-8ea9-96e27364051a",
      "artifact_version_id": "b1183849-776a-44bf-8ea9-96e27364051a-v001",
      "created_at": "2025-10-05T23:39:00+09:00",
      "updated_at": "2025-10-05T23:45:00+09:00"
    },
    {
      "slug": "child_neglect",
      "title": {
        "en": "Addressing Child Neglect Concerns",
        "vi": "Giải quyết Lo ngại Bỏ bê Trẻ"
      },
      "copy": {
        "en": "Ensure care, seek help, and report neglect immediately. Dare: Call hotline; ensure safety.",
        "vi": "Đảm bảo chăm sóc, tìm giúp đỡ, báo cáo bỏ bê ngay. Dám: Gọi đường dây nóng; đảm bảo an toàn."
      },
      "attribution": "Best Practices / Thực hành tốt nhất",
      "tags": ["parenting", "safety"],
      "urgency": "immediate",
      "severity_level": 5,
      "systems": ["child_development", "family"],
      "metadata": { "topic": "safety", "flags": ["crisis"] },
      "artifact_id": "c229495a-665b-45c0-8fba-87f38475051b",
      "artifact_version_id": "c229495a-665b-45c0-8fba-87f38475051b-v001",
      "created_at": "2025-10-05T23:39:00+09:00",
      "updated_at": "2025-10-05T23:45:00+09:00"
    },
    {
      "slug": "frustration",
      "title": {
        "en": "Handling Toddler Frustration",
        "vi": "Xử lý Bực bội của Bé"
      },
      "copy": {
        "en": "Validate their frustration, model calm, and offer comfort. Dare: Stay patient always.",
        "vi": "Xác nhận bực bội, làm gương bình tĩnh, an ủi. Dám: Luôn kiên nhẫn."
      },
      "attribution": "Best Practices / Thực hành tốt nhất",
      "tags": ["parenting", "emotions"],
      "urgency": "soon",
      "severity_level": 3,
      "systems": ["psychology", "child_development"],
      "metadata": { "topic": "emotional_regulation", "flags": ["sensitive"] },
      "artifact_id": "d33a5a6b-554c-46d1-9acb-78e49586051c",
      "artifact_version_id": "d33a5a6b-554c-46d1-9acb-78e49586051c-v001",
      "created_at": "2025-10-05T23:39:00+09:00",
      "updated_at": "2025-10-05T23:45:00+09:00"
    },
    {
      "slug": "sleep_issues",
      "title": {
        "en": "Addressing Toddler Sleep Issues",
        "vi": "Giải quyết Vấn đề Giấc ngủ của Bé"
      },
      "copy": {
        "en": "Maintain routines, limit stimulation, and comfort gently. Dare: Model healthy sleep habits.",
        "vi": "Duy trì thói quen, hạn chế kích thích, an ủi nhẹ nhàng. Dám: Làm gương giấc ngủ lành mạnh."
      },
      "attribution": "Best Practices / Thực hành tốt nhất",
      "tags": ["parenting", "health"],
      "urgency": "soon",
      "severity_level": 3,
      "systems": ["child_development", "psychology"],
      "metadata": { "topic": "health", "flags": ["sensitive"] },
      "artifact_id": "e44b6b7c-443d-47e2-8bde-69f5a697051d",
      "artifact_version_id": "e44b6b7c-443d-47e2-8bde-69f5a697051d-v001",
      "created_at": "2025-10-05T23:39:00+09:00",
      "updated_at": "2025-10-05T23:45:00+09:00"
    },
    {
      "slug": "social_skills",
      "title": {
        "en": "Fostering Toddler Social Skills",
        "vi": "Nuôi dưỡng Kỹ năng Xã hội cho Bé"
      },
      "copy": {
        "en": "Encourage playdates, model kindness, and teach cooperation. Dare: Guide social interactions.",
        "vi": "Khuyến khích chơi cùng bạn, làm gương tử tế, dạy hợp tác. Dám: Hướng dẫn tương tác xã hội."
      },
      "attribution": "Best Practices / Thực hành tốt nhất",
      "tags": ["parenting", "behavior"],
      "urgency": "routine",
      "severity_level": 2,
      "systems": ["child_development", "psychology"],
      "metadata": { "topic": "social_skills", "flags": [] },
      "artifact_id": "f55c7c8d-332e-48f3-9cef-5a06b7a8051e",
      "artifact_version_id": "f55c7c8d-332e-48f3-9cef-5a06b7a8051e-v001",
      "created_at": "2025-10-05T23:39:00+09:00",
      "updated_at": "2025-10-05T23:45:00+09:00"
    },
    {
      "slug": "potty_training",
      "title": {
        "en": "Guiding Potty Training",
        "vi": "Hướng dẫn Bé Tập Đi Vệ sinh"
      },
      "copy": {
        "en": "Be patient, celebrate successes, and avoid pressure. Dare: Follow their pace.",
        "vi": "Kiên nhẫn, tôn vinh thành công, tránh áp lực. Dám: Theo nhịp độ của bé."
      },
      "attribution": "Best Practices / Thực hành tốt nhất",
      "tags": ["parenting", "routine"],
      "urgency": "routine",
      "severity_level": 2,
      "systems": ["child_development", "family"],
      "metadata": { "topic": "routine", "flags": [] },
      "artifact_id": "065d8d9e-221f-41a4-8af1-49b7c8c9051f",
      "artifact_version_id": "065d8d9e-221f-41a4-8af1-49b7c8c9051f-v001",
      "created_at": "2025-10-05T23:39:00+09:00",
      "updated_at": "2025-10-05T23:45:00+09:00"
    },
    {
      "slug": "eating_habits",
      "title": {
        "en": "Encouraging Healthy Eating Habits",
        "vi": "Khuyến khích Thói quen Ăn uống Lành mạnh"
      },
      "copy": {
        "en": "Offer variety, model healthy eating, and avoid battles. Dare: Make meals fun.",
        "vi": "Cung cấp đa dạng, làm gương ăn lành mạnh, tránh tranh cãi. Dám: Làm bữa ăn vui vẻ."
      },
      "attribution": "Best Practices / Thực hành tốt nhất",
      "tags": ["parenting", "health"],
      "urgency": "routine",
      "severity_level": 2,
      "systems": ["child_development", "family"],
      "metadata": { "topic": "health", "flags": [] },
      "artifact_id": "176e9eaf-1100-42b5-8b02-38c8d9da0520",
      "artifact_version_id": "176e9eaf-1100-42b5-8b02-38c8d9da0520-v001",
      "created_at": "2025-10-05T23:39:00+09:00",
      "updated_at": "2025-10-05T23:45:00+09:00"
    },
    {
      "slug": "separation_anxiety",
      "title": {
        "en": "Managing Separation Anxiety",
        "vi": "Quản lý Lo âu Chia cách"
      },
      "copy": {
        "en": "Reassure gently, keep goodbyes short, and build trust. Dare: Stay calm during partings.",
        "vi": "Trấn an nhẹ nhàng, tạm biệt ngắn gọn, xây dựng lòng tin. Dám: Bình tĩnh khi chia tay."
      },
      "attribution": "Best Practices / Thực hành tốt nhất",
      "tags": ["parenting", "emotions"],
      "urgency": "soon",
      "severity_level": 3,
      "systems": ["psychology", "child_development"],
      "metadata": { "topic": "emotional_support", "flags": ["sensitive"] },
      "artifact_id": "287fafb0-ff11-43c6-9c13-27d9eaeb0521",
      "artifact_version_id": "287fafb0-ff11-43c6-9c13-27d9eaeb0521-v001",
      "created_at": "2025-10-05T23:39:00+09:00",
      "updated_at": "2025-10-05T23:45:00+09:00"
    },
    {
      "slug": "screen_time",
      "title": {
        "en": "Managing Toddler Screen Time",
        "vi": "Quản lý Thời gian Màn hình của Bé"
      },
      "copy": {
        "en": "Limit screens, engage in play, and model balance. Dare: Set strict screen boundaries.",
        "vi": "Hạn chế màn hình, tham gia chơi, làm gương cân bằng. Dám: Đặt giới hạn màn hình nghiêm ngặt."
      },
      "attribution": "Best Practices / Thực hành tốt nhất",
      "tags": ["parenting", "behavior"],
      "urgency": "routine",
      "severity_level": 2,
      "systems": ["child_development", "family"],
      "metadata": { "topic": "behavior", "flags": [] },
      "artifact_id": "3980b0c1-ee22-44d7-8d24-16ea0bfc0522",
      "artifact_version_id": "3980b0c1-ee22-44d7-8d24-16ea0bfc0522-v001",
      "created_at": "2025-10-05T23:39:00+09:00",
      "updated_at": "2025-10-05T23:45:00+09:00"
    },
    {
      "slug": "self_expression",
      "title": {
        "en": "Encouraging Toddler Self-Expression",
        "vi": "Khuyến khích Bé Tự Biểu đạt"
      },
      "copy": {
        "en": "Support creativity, validate their voice, and provide outlets. Dare: Celebrate their expression.",
        "vi": "Hỗ trợ sáng tạo, xác nhận tiếng nói, cung cấp lối thoát. Dám: Tôn vinh biểu đạt."
      },
      "attribution": "Best Practices / Thực hành tốt nhất",
      "tags": ["parenting", "growth"],
      "urgency": "routine",
      "severity_level": 2,
      "systems": ["child_development", "psychology"],
      "metadata": { "topic": "growth", "flags": [] },
      "artifact_id": "4a91c1d2-dd33-45e8-9e35-05fb1c0d0523",
      "artifact_version_id": "4a91c1d2-dd33-45e8-9e35-05fb1c0d0523-v001",
      "created_at": "2025-10-05T23:39:00+09:00",
      "updated_at": "2025-10-05T23:45:00+09:00"
    },
    {
      "slug": "transitions",
      "title": {
        "en": "Helping Toddlers with Transitions",
        "vi": "Giúp Bé với Chuyển đổi"
      },
      "copy": {
        "en": "Prepare them gently, use routines, and offer comfort. Dare: Guide transitions calmly.",
        "vi": "Chuẩn bị nhẹ nhàng, dùng thói quen, an ủi. Dám: Hướng dẫn chuyển đổi bình tĩnh."
      },
      "attribution": "Best Practices / Thực hành tốt nhất",
      "tags": ["parenting", "routine"],
      "urgency": "soon",
      "severity_level": 3,
      "systems": ["child_development", "psychology"],
      "metadata": { "topic": "routine", "flags": [] },
      "artifact_id": "5ba2d2e3-cc44-46f9-8f46-f6ac2d1e0524",
      "artifact_version_id": "5ba2d2e3-cc44-46f9-8f46-f6ac2d1e0524-v001",
      "created_at": "2025-10-05T23:39:00+09:00",
      "updated_at": "2025-10-05T23:45:00+09:00"
    },
    {
      "slug": "biting",
      "title": { "en": "Addressing Toddler Biting", "vi": "Xử lý Bé Cắn" },
      "copy": {
        "en": "Redirect calmly, teach alternatives, and model gentle behavior. Dare: Stay consistent.",
        "vi": "Chuyển hướng bình tĩnh, dạy cách thay thế, làm gương nhẹ nhàng. Dám: Duy trì nhất quán."
      },
      "attribution": "Best Practices / Thực hành tốt nhất",
      "tags": ["parenting", "behavior"],
      "urgency": "soon",
      "severity_level": 3,
      "systems": ["child_development", "psychology"],
      "metadata": { "topic": "behavior", "flags": ["sensitive"] },
      "artifact_id": "6cb3e3f4-bb55-470a-9a57-e7bd3e2f0525",
      "artifact_version_id": "6cb3e3f4-bb55-470a-9a57-e7bd3e2f0525-v001",
      "created_at": "2025-10-05T23:39:00+09:00",
      "updated_at": "2025-10-05T23:45:00+09:00"
    },
    {
      "slug": "hitting",
      "title": { "en": "Addressing Toddler Hitting", "vi": "Xử lý Bé Đánh" },
      "copy": {
        "en": "Stop gently, teach kindness, and redirect to safe actions. Dare: Model gentle touch.",
        "vi": "Ngăn nhẹ nhàng, dạy tử tế, chuyển hướng hành động an toàn. Dám: Làm gương tiếp xúc nhẹ."
      },
      "attribution": "Best Practices / Thực hành tốt nhất",
      "tags": ["parenting", "behavior"],
      "urgency": "soon",
      "severity_level": 3,
      "systems": ["child_development", "psychology"],
      "metadata": { "topic": "behavior", "flags": ["sensitive"] },
      "artifact_id": "7dc4f405-aa66-481b-8b68-d8ce4f300526",
      "artifact_version_id": "7dc4f405-aa66-481b-8b68-d8ce4f300526-v001",
      "created_at": "2025-10-05T23:39:00+09:00",
      "updated_at": "2025-10-05T23:45:00+09:00"
    },
    {
      "slug": "elopement",
      "title": {
        "en": "Preventing Toddler Elopement",
        "vi": "Ngăn Bé Bỏ chạy"
      },
      "copy": {
        "en": "Supervise closely, secure exits, and teach safety rules. Dare: Call hotline; ensure safety.",
        "vi": "Giám sát chặt, bảo vệ lối ra, dạy quy tắc an toàn. Dám: Gọi đường dây nóng; đảm bảo an toàn."
      },
      "attribution": "Best Practices / Thực hành tốt nhất",
      "tags": ["parenting", "safety"],
      "urgency": "immediate",
      "severity_level": 5,
      "systems": ["child_development", "family"],
      "metadata": { "topic": "safety", "flags": ["crisis"] },
      "artifact_id": "8ed50516-9967-492c-9c79-c9df50310527",
      "artifact_version_id": "8ed50516-9967-492c-9c79-c9df50310527-v001",
      "created_at": "2025-10-05T23:39:00+09:00",
      "updated_at": "2025-10-05T23:45:00+09:00"
    },
    {
      "slug": "parental_stress",
      "title": {
        "en": "Managing Parental Stress",
        "vi": "Quản lý Căng thẳng Cha mẹ"
      },
      "copy": {
        "en": "Practice self-care, seek support, and model calm resilience. Dare: Prioritize your peace.",
        "vi": "Tự chăm sóc, tìm hỗ trợ, làm gương kiên cường bình tĩnh. Dám: Ưu tiên sự bình yên."
      },
      "attribution": "Best Practices / Thực hành tốt nhất",
      "tags": ["parenting", "emotions"],
      "urgency": "soon",
      "severity_level": 3,
      "systems": ["psychology", "family"],
      "metadata": { "topic": "self_care", "flags": ["sensitive"] },
      "artifact_id": "e43b6b7c-3303-4f82-8bd5-69f5a697052d",
      "artifact_version_id": "e43b6b7c-3303-4f82-8bd5-69f5a697052d-v001",
      "created_at": "2025-10-05T23:39:00+09:00",
      "updated_at": "2025-10-05T23:45:00+09:00"
    },
    {
      "slug": "trust",
      "title": {
        "en": "Building Trust with Your Toddler",
        "vi": "Xây dựng Lòng tin với Bé"
      },
      "copy": {
        "en": "Be reliable, respond warmly, and honor their needs. Dare: Build secure attachment.",
        "vi": "Đáng tin cậy, phản hồi ấm áp, tôn trọng nhu cầu. Dám: Xây dựng gắn bó an toàn."
      },
      "attribution": "Best Practices / Thực hành tốt nhất",
      "tags": ["parenting", "emotions"],
      "urgency": "routine",
      "severity_level": 2,
      "systems": ["psychology", "child_development"],
      "metadata": { "topic": "emotional_support", "flags": [] },
      "artifact_id": "f54c7c8d-22f2-4a93-9c26-5a06b7a8052e",
      "artifact_version_id": "f54c7c8d-22f2-4a93-9c26-5a06b7a8052e-v001",
      "created_at": "2025-10-05T23:39:00+09:00",
      "updated_at": "2025-10-05T23:45:00+09:00"
    }
  ]
}
