{
  "id": "public_speaking_kids_l3",
  "tier": "Kids Level 3 / Trẻ Em Cấp 3",
  "title": {
    "en": "Public Speaking",
    "vi": "Nói Trước Công Chúng"
  },
  "intro": {
    "en": "Build confidence in public speaking and presentations.",
    "vi": "Xây dựng sự tự tin trong việc nói trước công chúng và thuyết trình."
  },
  "intro_audio": "",
  "entries": [],
  "meta": {
    "age_range": "10-12",
    "level": "Kids Level 3",
    "created_at": "2025-11-23T00:00:00.000Z",
    "updated_at": "2025-11-23T00:00:00.000Z",
    "num_entries": 0,
    "room_color": "#F8BBD0"
  }
}