{
  "name": "Money Basics You Should’ve Learned",
  "name_vi": "Kiến Thức Tiền Bạc Nên Được Dạy",
  "description": "No shame, no jargon. Just the simple tools to see your money clearly — and start today.",
  "description_vi": "Không xấu hổ, không thuật ngữ. Chỉ những công cụ đơn giản để thấy rõ tiền của bạn — và bắt đầu hôm nay.",
  "keywords_en": [
    "money basics",
    "snapshot",
    "income",
    "spending",
    "saving",
    "debt"
  ],
  "keywords_vi": [
    "kiến thức cơ bản tiền",
    "ảnh chụp",
    "thu nhập",
    "chi tiêu",
    "tiết kiệm",
    "nợ"
  ],
  "entries": []
}
