{
  "tier": "VIP 3",
  "title": {
    "en": "Strategy in Life - Mastery & Legacy",
    "vi": "Chiến Lược Cuộc Sống - Tinh Thông & Di Sản"
  },
  "content": {
    "en": "The pinnacle of strategic wisdom. Build lasting impact, create generational value, and master the grand game of life.",
    "vi": "Đỉnh cao của trí tuệ chiến lược. Xây dựng tác động bền vững, tạo ra giá trị nhiều thế hệ và làm chủ trò chơi vĩ đại của cuộc đời."
  },
  "entries": [
    {
      "title": "Room 1 - Grand Strategy",
      "content": "Content pending. Life as a masterpiece.",
      "audio": "strategy_life_3_vip3_room_01.mp3"
    },
    {
      "title": "Room 2 - Visionary Leadership",
      "content": "Content pending. Leading generations.",
      "audio": "strategy_life_3_vip3_room_02.mp3"
    },
    {
      "title": "Room 3 - Empire Building",
      "content": "Content pending. Creating lasting institutions.",
      "audio": "strategy_life_3_vip3_room_03.mp3"
    },
    {
      "title": "Room 4 - Wisdom Cultivation",
      "content": "Content pending. Deep understanding.",
      "audio": "strategy_life_3_vip3_room_04.mp3"
    },
    {
      "title": "Room 5 - Strategic Philosophy",
      "content": "Content pending. Principles that endure.",
      "audio": "strategy_life_3_vip3_room_05.mp3"
    },
    {
      "title": "Room 6 - Generational Wealth",
      "content": "Content pending. Legacy beyond money.",
      "audio": "strategy_life_3_vip3_room_06.mp3"
    },
    {
      "title": "Room 7 - Cultural Impact",
      "content": "Content pending. Shaping society.",
      "audio": "strategy_life_3_vip3_room_07.mp3"
    },
    {
      "title": "Room 8 - Strategic Teaching",
      "content": "Content pending. Passing wisdom forward.",
      "audio": "strategy_life_3_vip3_room_08.mp3"
    },
    {
      "title": "Room 9 - Ecosystem Creation",
      "content": "Content pending. Building communities.",
      "audio": "strategy_life_3_vip3_room_09.mp3"
    },
    {
      "title": "Room 10 - Paradigm Shifts",
      "content": "Content pending. Changing the game.",
      "audio": "strategy_life_3_vip3_room_10.mp3"
    },
    {
      "title": "Room 11 - Strategic Mentorship",
      "content": "Content pending. Developing future leaders.",
      "audio": "strategy_life_3_vip3_room_11.mp3"
    },
    {
      "title": "Room 12 - Timeless Principles",
      "content": "Content pending. Universal strategies.",
      "audio": "strategy_life_3_vip3_room_12.mp3"
    },
    {
      "title": "Room 13 - Long-Game Mastery",
      "content": "Content pending. Thinking in decades.",
      "audio": "strategy_life_3_vip3_room_13.mp3"
    },
    {
      "title": "Room 14 - Strategic Wisdom",
      "content": "Content pending. Knowledge into insight.",
      "audio": "strategy_life_3_vip3_room_14.mp3"
    },
    {
      "title": "Room 15 - Legacy Architecture",
      "content": "Content pending. Designing your impact.",
      "audio": "strategy_life_3_vip3_room_15.mp3"
    },
    {
      "title": "Room 16 - Global Thinking",
      "content": "Content pending. Worldwide perspective.",
      "audio": "strategy_life_3_vip3_room_16.mp3"
    },
    {
      "title": "Room 17 - Strategic Humility",
      "content": "Content pending. Power in service.",
      "audio": "strategy_life_3_vip3_room_17.mp3"
    },
    {
      "title": "Room 18 - Transformation Leadership",
      "content": "Content pending. Catalyzing change.",
      "audio": "strategy_life_3_vip3_room_18.mp3"
    },
    {
      "title": "Room 19 - Strategic Values",
      "content": "Content pending. Character-driven success.",
      "audio": "strategy_life_3_vip3_room_19.mp3"
    },
    {
      "title": "Room 20 - Ancestral Wisdom",
      "content": "Content pending. Learning from history.",
      "audio": "strategy_life_3_vip3_room_20.mp3"
    },
    {
      "title": "Room 21 - Future Visioning",
      "content": "Content pending. Creating tomorrow.",
      "audio": "strategy_life_3_vip3_room_21.mp3"
    },
    {
      "title": "Room 22 - Strategic Compassion",
      "content": "Content pending. Leading with heart.",
      "audio": "strategy_life_3_vip3_room_22.mp3"
    },
    {
      "title": "Room 23 - System Transformation",
      "content": "Content pending. Changing structures.",
      "audio": "strategy_life_3_vip3_room_23.mp3"
    },
    {
      "title": "Room 24 - Stewardship Strategy",
      "content": "Content pending. Caring for what matters.",
      "audio": "strategy_life_3_vip3_room_24.mp3"
    },
    {
      "title": "Room 25 - Strategic Integration",
      "content": "Content pending. Wholeness in action.",
      "audio": "strategy_life_3_vip3_room_25.mp3"
    },
    {
      "title": "Room 26 - Master's Mindset",
      "content": "Content pending. Thinking at the highest level.",
      "audio": "strategy_life_3_vip3_room_26.mp3"
    },
    {
      "title": "Room 27 - Eternal Impact",
      "content": "Content pending. Beyond your lifetime.",
      "audio": "strategy_life_3_vip3_room_27.mp3"
    },
    {
      "title": "Room 28 - Strategic Fulfillment",
      "content": "Content pending. Success with meaning.",
      "audio": "strategy_life_3_vip3_room_28.mp3"
    },
    {
      "title": "Room 29 - The Complete Strategist",
      "content": "Content pending. Integration of all elements.",
      "audio": "strategy_life_3_vip3_room_29.mp3"
    },
    {
      "title": "Room 30 - Living Legacy",
      "content": "Content pending. Your eternal strategy.",
      "audio": "strategy_life_3_vip3_room_30.mp3"
    }
  ],
  "keywords": {
    "personalized_strategy_life_3": {
      "en": [
        "mastery",
        "legacy",
        "wisdom",
        "leadership",
        "impact",
        "transformation",
        "vision",
        "fulfillment"
      ],
      "vi": [
        "tinh thông",
        "di sản",
        "trí tuệ",
        "lãnh đạo",
        "tác động",
        "biến đổi",
        "tầm nhìn",
        "viên mãn"
      ]
    }
  },
  "meta": {
    "created_at": "2025-01-15T10:00:00+00:00",
    "updated_at": "2025-01-15T10:00:00+00:00",
    "entry_count": 30,
    "artifact_set_id": "strategy-life-3-vip3-2025",
    "data_format_version": "MercyBlade-Core-v1.2",
    "room_color": "#059669",
    "special_theme": "strategic",
    "tier": "vip3"
  }
}