{
  "name": "Stress Management & Resilience",
  "name_vi": "Quản Lý Căng Thẳng & Sức Bền Tinh Thần",
  "description": "Expert techniques to master stress reduction, mindfulness, and inner calm",
  "description_vi": "Các kỹ thuật chuyên gia để làm chủ giảm căng thẳng, chánh niệm và bình an nội tại",
  "keywords_en": [
    "mastered breathing",
    "deep mindfulness practices",
    "sustained stress routines",
    "resilience self-talk",
    "exercise for stress",
    "social support stress relief"
  ],
  "keywords_vi": [
    "làm chủ hít thở",
    "thực hành chánh niệm sâu sắc",
    "thói quen giảm căng thẳng bền vững",
    "tự nói kiên cường",
    "tập thể dục giảm căng thẳng",
    "hỗ trợ xã hội giảm căng thẳng"
  ],
  "entries": [],
  "keywords": {
    "personalized_stress_management": {
      "en": [
        "mastered breathing",
        "deep mindfulness practices",
        "sustained stress routines",
        "resilience self-talk",
        "exercise for stress",
        "social support stress relief"
      ],
      "vi": [
        "làm chủ hít thở",
        "thực hành chánh niệm sâu sắc",
        "thói quen giảm căng thẳng bền vững",
        "tự nói kiên cường",
        "tập thể dục giảm căng thẳng",
        "hỗ trợ xã hội giảm căng thẳng"
      ]
    }
  },
  "id": "stress_vip3",
  "title": {
    "en": "Stress Management & Resilience",
    "vi": "Quản Lý Căng Thẳng & Sức Bền Tinh Thần"
  },
  "content": {
    "en": "Expert techniques to master stress reduction, mindfulness, and inner calm",
    "vi": "Các kỹ thuật chuyên gia để làm chủ giảm căng thẳng, chánh niệm và bình an nội tại"
  },
  "tier": "VIP3",
  "domain": "Mental Health"
}
